{"licenses":[{"name":"","id":0,"url":""}],"info":{"contributor":"","date_created":"","description":"","url":"","version":"","year":""},"categories":[{"id":1,"name":"defect","supercategory":""}],"images":[{"id":1,"width":960,"height":1280,"file_name":"1740815649.322543.jpg","license":0,"flickr_url":"","coco_url":"","date_captured":0},{"id":2,"width":960,"height":1280,"file_name":"1740817119.43072.jpg","license":0,"flickr_url":"","coco_url":"","date_captured":0},{"id":3,"width":1280,"height":960,"file_name":"1741083042.638356.jpg","license":0,"flickr_url":"","coco_url":"","date_captured":0},{"id":4,"width":721,"height":1280,"file_name":"1741454540.423105.jpg","license":0,"flickr_url":"","coco_url":"","date_captured":0},{"id":5,"width":721,"height":1280,"file_name":"1741454565.8951442.jpg","license":0,"flickr_url":"","coco_url":"","date_captured":0},{"id":6,"width":721,"height":1280,"file_name":"1741454606.1934314.jpg","license":0,"flickr_url":"","coco_url":"","date_captured":0},{"id":7,"width":1280,"height":577,"file_name":"1741665676.4356358.jpg","license":0,"flickr_url":"","coco_url":"","date_captured":0},{"id":8,"width":591,"height":1280,"file_name":"1741692730.975851.jpg","license":0,"flickr_url":"","coco_url":"","date_captured":0},{"id":9,"width":591,"height":1280,"file_name":"1741692750.8275876.jpg","license":0,"flickr_url":"","coco_url":"","date_captured":0},{"id":10,"width":591,"height":1280,"file_name":"1741692768.5585155.jpg","license":0,"flickr_url":"","coco_url":"","date_captured":0},{"id":11,"width":960,"height":1280,"file_name":"1741838391.0521846.jpg","license":0,"flickr_url":"","coco_url":"","date_captured":0},{"id":12,"width":960,"height":1280,"file_name":"1741838391.0575278.jpg","license":0,"flickr_url":"","coco_url":"","date_captured":0},{"id":13,"width":960,"height":1280,"file_name":"1741838391.1526966.jpg","license":0,"flickr_url":"","coco_url":"","date_captured":0},{"id":14,"width":960,"height":1280,"file_name":"1741838391.2925956.jpg","license":0,"flickr_url":"","coco_url":"","date_captured":0},{"id":15,"width":960,"height":1280,"file_name":"1741838391.380439.jpg","license":0,"flickr_url":"","coco_url":"","date_captured":0},{"id":16,"width":960,"height":1280,"file_name":"1741838391.3959591.jpg","license":0,"flickr_url":"","coco_url":"","date_captured":0},{"id":17,"width":960,"height":1280,"file_name":"1741838391.4386482.jpg","license":0,"flickr_url":"","coco_url":"","date_captured":0},{"id":18,"width":960,"height":1280,"file_name":"1741838391.4464128.jpg","license":0,"flickr_url":"","coco_url":"","date_captured":0},{"id":19,"width":1280,"height":720,"file_name":"1741838391.4773273.jpg","license":0,"flickr_url":"","coco_url":"","date_captured":0},{"id":20,"width":960,"height":1280,"file_name":"1741838391.5620337.jpg","license":0,"flickr_url":"","coco_url":"","date_captured":0},{"id":21,"width":960,"height":1280,"file_name":"1741838391.6110563.jpg","license":0,"flickr_url":"","coco_url":"","date_captured":0},{"id":22,"width":960,"height":1280,"file_name":"1741838391.7036808.jpg","license":0,"flickr_url":"","coco_url":"","date_captured":0},{"id":23,"width":960,"height":1280,"file_name":"1741838391.7968318.jpg","license":0,"flickr_url":"","coco_url":"","date_captured":0},{"id":24,"width":960,"height":1280,"file_name":"1741838391.9626296.jpg","license":0,"flickr_url":"","coco_url":"","date_captured":0},{"id":25,"width":960,"height":1280,"file_name":"1741838391.9994538.jpg","license":0,"flickr_url":"","coco_url":"","date_captured":0},{"id":26,"width":960,"height":1280,"file_name":"1741838393.270437.jpg","license":0,"flickr_url":"","coco_url":"","date_captured":0},{"id":27,"width":720,"height":1280,"file_name":"1741932761.1629546.jpg","license":0,"flickr_url":"","coco_url":"","date_captured":0},{"id":28,"width":720,"height":1280,"file_name":"1741932971.9898655.jpg","license":0,"flickr_url":"","coco_url":"","date_captured":0},{"id":29,"width":720,"height":1280,"file_name":"1742009468.2241704.jpg","license":0,"flickr_url":"","coco_url":"","date_captured":0},{"id":30,"width":963,"height":1280,"file_name":"1742009633.9275823.jpg","license":0,"flickr_url":"","coco_url":"","date_captured":0},{"id":31,"width":963,"height":1280,"file_name":"1742009634.042336.jpg","license":0,"flickr_url":"","coco_url":"","date_captured":0},{"id":32,"width":963,"height":1280,"file_name":"1742009634.0752196.jpg","license":0,"flickr_url":"","coco_url":"","date_captured":0},{"id":33,"width":963,"height":1280,"file_name":"1742009634.0916698.jpg","license":0,"flickr_url":"","coco_url":"","date_captured":0},{"id":34,"width":963,"height":1280,"file_name":"1742009634.093746.jpg","license":0,"flickr_url":"","coco_url":"","date_captured":0},{"id":35,"width":963,"height":1280,"file_name":"1742009634.1078656.jpg","license":0,"flickr_url":"","coco_url":"","date_captured":0},{"id":36,"width":960,"height":1280,"file_name":"1742094361.4987469.jpg","license":0,"flickr_url":"","coco_url":"","date_captured":0},{"id":37,"width":960,"height":1280,"file_name":"1742097338.1136467.jpg","license":0,"flickr_url":"","coco_url":"","date_captured":0},{"id":38,"width":960,"height":1280,"file_name":"1742127906.4958909.jpg","license":0,"flickr_url":"","coco_url":"","date_captured":0},{"id":39,"width":1280,"height":961,"file_name":"1742185933.334592.jpg","license":0,"flickr_url":"","coco_url":"","date_captured":0},{"id":40,"width":720,"height":1280,"file_name":"1742186700.8160505.jpg","license":0,"flickr_url":"","coco_url":"","date_captured":0},{"id":41,"width":964,"height":1280,"file_name":"1742286284.4849048.jpg","license":0,"flickr_url":"","coco_url":"","date_captured":0},{"id":42,"width":960,"height":1280,"file_name":"1742391868.5838523.jpg","license":0,"flickr_url":"","coco_url":"","date_captured":0},{"id":43,"width":960,"height":1280,"file_name":"1742391868.749053.jpg","license":0,"flickr_url":"","coco_url":"","date_captured":0},{"id":44,"width":960,"height":1280,"file_name":"1742391868.7865055.jpg","license":0,"flickr_url":"","coco_url":"","date_captured":0},{"id":45,"width":960,"height":1280,"file_name":"1742391868.8596.jpg","license":0,"flickr_url":"","coco_url":"","date_captured":0},{"id":46,"width":960,"height":1280,"file_name":"1742391868.9034762.jpg","license":0,"flickr_url":"","coco_url":"","date_captured":0},{"id":47,"width":960,"height":1280,"file_name":"1742391868.9515252.jpg","license":0,"flickr_url":"","coco_url":"","date_captured":0},{"id":48,"width":960,"height":1280,"file_name":"1742391869.0135257.jpg","license":0,"flickr_url":"","coco_url":"","date_captured":0},{"id":49,"width":960,"height":1280,"file_name":"1742391869.0166914.jpg","license":0,"flickr_url":"","coco_url":"","date_captured":0},{"id":50,"width":960,"height":1280,"file_name":"1742397892.0643413.jpg","license":0,"flickr_url":"","coco_url":"","date_captured":0},{"id":51,"width":960,"height":1280,"file_name":"1742397951.9046743.jpg","license":0,"flickr_url":"","coco_url":"","date_captured":0},{"id":52,"width":960,"height":1280,"file_name":"1742397985.6547475.jpg","license":0,"flickr_url":"","coco_url":"","date_captured":0},{"id":53,"width":960,"height":1280,"file_name":"1742398021.5269265.jpg","license":0,"flickr_url":"","coco_url":"","date_captured":0},{"id":54,"width":960,"height":1280,"file_name":"1742405803.9216022.jpg","license":0,"flickr_url":"","coco_url":"","date_captured":0},{"id":55,"width":960,"height":1280,"file_name":"1742418478.2715716.jpg","license":0,"flickr_url":"","coco_url":"","date_captured":0},{"id":56,"width":960,"height":1280,"file_name":"1742423086.0394015.jpg","license":0,"flickr_url":"","coco_url":"","date_captured":0},{"id":57,"width":960,"height":1280,"file_name":"1742471968.3637671.jpg","license":0,"flickr_url":"","coco_url":"","date_captured":0},{"id":58,"width":960,"height":1280,"file_name":"1742473672.0586693.jpg","license":0,"flickr_url":"","coco_url":"","date_captured":0},{"id":59,"width":960,"height":1280,"file_name":"1742475972.7588713.jpg","license":0,"flickr_url":"","coco_url":"","date_captured":0},{"id":60,"width":960,"height":1280,"file_name":"1742475972.7822344.jpg","license":0,"flickr_url":"","coco_url":"","date_captured":0},{"id":61,"width":960,"height":1280,"file_name":"1742475972.786736.jpg","license":0,"flickr_url":"","coco_url":"","date_captured":0},{"id":62,"width":960,"height":1280,"file_name":"1742475972.8065293.jpg","license":0,"flickr_url":"","coco_url":"","date_captured":0},{"id":63,"width":960,"height":1280,"file_name":"1742475972.8151417.jpg","license":0,"flickr_url":"","coco_url":"","date_captured":0},{"id":64,"width":960,"height":1280,"file_name":"1742475972.836422.jpg","license":0,"flickr_url":"","coco_url":"","date_captured":0},{"id":65,"width":960,"height":1280,"file_name":"1742475972.8514688.jpg","license":0,"flickr_url":"","coco_url":"","date_captured":0},{"id":66,"width":960,"height":1280,"file_name":"1742475972.8647013.jpg","license":0,"flickr_url":"","coco_url":"","date_captured":0},{"id":67,"width":960,"height":1280,"file_name":"1742475972.9029312.jpg","license":0,"flickr_url":"","coco_url":"","date_captured":0},{"id":68,"width":960,"height":1280,"file_name":"1742475973.3015165.jpg","license":0,"flickr_url":"","coco_url":"","date_captured":0},{"id":69,"width":960,"height":1280,"file_name":"1742475973.334501.jpg","license":0,"flickr_url":"","coco_url":"","date_captured":0},{"id":70,"width":960,"height":1280,"file_name":"1742475973.366283.jpg","license":0,"flickr_url":"","coco_url":"","date_captured":0},{"id":71,"width":960,"height":1280,"file_name":"1742475973.4022098.jpg","license":0,"flickr_url":"","coco_url":"","date_captured":0},{"id":72,"width":960,"height":1280,"file_name":"1742475973.5834458.jpg","license":0,"flickr_url":"","coco_url":"","date_captured":0},{"id":73,"width":960,"height":1280,"file_name":"1742478233.7804127.jpg","license":0,"flickr_url":"","coco_url":"","date_captured":0},{"id":74,"width":960,"height":1280,"file_name":"1742493314.7702997.jpg","license":0,"flickr_url":"","coco_url":"","date_captured":0},{"id":75,"width":960,"height":1280,"file_name":"1742493314.798474.jpg","license":0,"flickr_url":"","coco_url":"","date_captured":0},{"id":76,"width":591,"height":1280,"file_name":"1742496489.273166.jpg","license":0,"flickr_url":"","coco_url":"","date_captured":0},{"id":77,"width":591,"height":1280,"file_name":"1742496506.8942149.jpg","license":0,"flickr_url":"","coco_url":"","date_captured":0},{"id":78,"width":591,"height":1280,"file_name":"1742496534.8564503.jpg","license":0,"flickr_url":"","coco_url":"","date_captured":0},{"id":79,"width":591,"height":1280,"file_name":"1742496550.1749983.jpg","license":0,"flickr_url":"","coco_url":"","date_captured":0},{"id":80,"width":960,"height":1280,"file_name":"1742774204.1648624.jpg","license":0,"flickr_url":"","coco_url":"","date_captured":0},{"id":81,"width":960,"height":1280,"file_name":"1742774204.1797655.jpg","license":0,"flickr_url":"","coco_url":"","date_captured":0},{"id":82,"width":960,"height":1280,"file_name":"1742883000.8511267.jpg","license":0,"flickr_url":"","coco_url":"","date_captured":0},{"id":83,"width":960,"height":1280,"file_name":"1743214142.2180073.jpg","license":0,"flickr_url":"","coco_url":"","date_captured":0},{"id":84,"width":960,"height":1280,"file_name":"1743214142.285887.jpg","license":0,"flickr_url":"","coco_url":"","date_captured":0},{"id":85,"width":720,"height":1280,"file_name":"1743269368.1098087.jpg","license":0,"flickr_url":"","coco_url":"","date_captured":0},{"id":86,"width":720,"height":1280,"file_name":"1743269394.7315445.jpg","license":0,"flickr_url":"","coco_url":"","date_captured":0},{"id":87,"width":960,"height":1280,"file_name":"1743319448.2384574.jpg","license":0,"flickr_url":"","coco_url":"","date_captured":0},{"id":88,"width":960,"height":1280,"file_name":"1743319448.2668204.jpg","license":0,"flickr_url":"","coco_url":"","date_captured":0},{"id":89,"width":960,"height":1280,"file_name":"1743319448.3067648.jpg","license":0,"flickr_url":"","coco_url":"","date_captured":0},{"id":90,"width":720,"height":1280,"file_name":"1743343128.0713983.jpg","license":0,"flickr_url":"","coco_url":"","date_captured":0},{"id":91,"width":960,"height":1280,"file_name":"1743370894.5805469.jpg","license":0,"flickr_url":"","coco_url":"","date_captured":0},{"id":92,"width":720,"height":1280,"file_name":"1743491206.751618.jpg","license":0,"flickr_url":"","coco_url":"","date_captured":0},{"id":93,"width":964,"height":1280,"file_name":"1743590656.6191318.jpg","license":0,"flickr_url":"","coco_url":"","date_captured":0},{"id":94,"width":964,"height":1280,"file_name":"1743590656.6208844.jpg","license":0,"flickr_url":"","coco_url":"","date_captured":0},{"id":95,"width":720,"height":1280,"file_name":"1743758528.4982095.jpg","license":0,"flickr_url":"","coco_url":"","date_captured":0},{"id":96,"width":720,"height":1280,"file_name":"1743758592.611449.jpg","license":0,"flickr_url":"","coco_url":"","date_captured":0},{"id":97,"width":720,"height":1280,"file_name":"1743760737.8088503.jpg","license":0,"flickr_url":"","coco_url":"","date_captured":0}],"annotations":[{"id":1,"image_id":1,"category_id":1,"segmentation":[],"area":772.6611999999994,"bbox":[441.93,470.66,22.52,34.31],"iscrowd":0,"attributes":{"occluded":false,"rotation":0.0}},{"id":2,"image_id":2,"category_id":1,"segmentation":[],"area":530.2494000000002,"bbox":[441.93,473.88,20.07,26.42],"iscrowd":0,"attributes":{"occluded":false,"rotation":0.0}},{"id":3,"image_id":3,"category_id":1,"segmentation":[],"area":581.4374000000045,"bbox":[552.26,484.24,7.31,79.54],"iscrowd":0,"attributes":{"occluded":false,"rotation":0.0}},{"id":4,"image_id":3,"category_id":1,"segmentation":[],"area":329.7999999999977,"bbox":[558.2,407.4,9.7,34.0],"iscrowd":0,"attributes":{"occluded":false,"rotation":0.0}},{"id":5,"image_id":4,"category_id":1,"segmentation":[],"area":48821.74049999996,"bbox":[298.73,242.18,61.23,797.35],"iscrowd":0,"attributes":{"occluded":false,"rotation":0.0}},{"id":6,"image_id":5,"category_id":1,"segmentation":[],"area":17245.61710000003,"bbox":[352.39,246.3,24.77,696.23],"iscrowd":0,"attributes":{"occluded":false,"rotation":0.0}},{"id":7,"image_id":6,"category_id":1,"segmentation":[],"area":25447.799300000013,"bbox":[356.52,424.49,51.59,493.27],"iscrowd":0,"attributes":{"occluded":false,"rotation":0.0}},{"id":8,"image_id":7,"category_id":1,"segmentation":[],"area":661.7969999999978,"bbox":[655.19,261.85,19.3,34.29],"iscrowd":0,"attributes":{"occluded":false,"rotation":0.0}},{"id":9,"image_id":8,"category_id":1,"segmentation":[],"area":11342.338000000007,"bbox":[276.7,226.9,17.8,637.21],"iscrowd":0,"attributes":{"occluded":false,"rotation":0.0}},{"id":10,"image_id":9,"category_id":1,"segmentation":[],"area":2320.2724999999978,"bbox":[306.27,559.71,75.95,30.55],"iscrowd":0,"attributes":{"occluded":false,"rotation":0.0}},{"id":11,"image_id":10,"category_id":1,"segmentation":[],"area":43124.48250000002,"bbox":[213.48,116.89,63.25,681.81],"iscrowd":0,"attributes":{"occluded":false,"rotation":0.0}},{"id":12,"image_id":11,"category_id":1,"segmentation":[],"area":71076.13,"bbox":[368.5,206.94,142.58,498.5],"iscrowd":0,"attributes":{"occluded":false,"rotation":0.0}},{"id":13,"image_id":11,"category_id":1,"segmentation":[],"area":22713.720399999987,"bbox":[479.99,823.36,115.78,196.18],"iscrowd":0,"attributes":{"occluded":false,"rotation":0.0}},{"id":14,"image_id":12,"category_id":1,"segmentation":[],"area":35579.2512,"bbox":[446.76,606.81,85.76,414.87],"iscrowd":0,"attributes":{"occluded":false,"rotation":0.0}},{"id":15,"image_id":12,"category_id":1,"segmentation":[],"area":12686.7684,"bbox":[389.83,318.01,88.98,142.58],"iscrowd":0,"attributes":{"occluded":false,"rotation":0.0}},{"id":16,"image_id":13,"category_id":1,"segmentation":[],"area":42395.106599999985,"bbox":[451.04,247.68,56.82,746.13],"iscrowd":0,"attributes":{"occluded":false,"rotation":0.0}},{"id":17,"image_id":14,"category_id":1,"segmentation":[],"area":13754.960599999995,"bbox":[408.06,389.83,45.02,305.53],"iscrowd":0,"attributes":{"occluded":false,"rotation":0.0}},{"id":18,"image_id":15,"category_id":1,"segmentation":[],"area":5608.500299999998,"bbox":[432.82,476.02,65.39,85.77],"iscrowd":0,"attributes":{"occluded":false,"rotation":0.0}},{"id":19,"image_id":15,"category_id":1,"segmentation":[],"area":140.3009999999993,"bbox":[383.8,795.49,11.9,11.79],"iscrowd":0,"attributes":{"occluded":false,"rotation":0.0}},{"id":20,"image_id":16,"category_id":1,"segmentation":[],"area":292.97759999999926,"bbox":[459.41,452.44,18.22,16.08],"iscrowd":0,"attributes":{"occluded":false,"rotation":0.0}},{"id":21,"image_id":16,"category_id":1,"segmentation":[],"area":99106.4643,"bbox":[380.08,390.26,188.67,525.29],"iscrowd":0,"attributes":{"occluded":false,"rotation":0.0}},{"id":22,"image_id":17,"category_id":1,"segmentation":[],"area":47181.76450000002,"bbox":[449.76,573.58,73.97,637.85],"iscrowd":0,"attributes":{"occluded":false,"rotation":0.0}},{"id":23,"image_id":17,"category_id":1,"segmentation":[],"area":134376.9989,"bbox":[335.05,199.44,346.27,388.07],"iscrowd":0,"attributes":{"occluded":false,"rotation":0.0}},{"id":24,"image_id":18,"category_id":1,"segmentation":[],"area":189.90480000000028,"bbox":[94.9,665.77,11.81,16.08],"iscrowd":0,"attributes":{"occluded":false,"rotation":0.0}},{"id":25,"image_id":18,"category_id":1,"segmentation":[],"area":2227.4595,"bbox":[433.68,607.88,36.45,61.11],"iscrowd":0,"attributes":{"occluded":false,"rotation":0.0}},{"id":26,"image_id":19,"category_id":1,"segmentation":[],"area":531.4234000000013,"bbox":[569.68,292.68,25.33,20.98],"iscrowd":0,"attributes":{"occluded":false,"rotation":0.0}},{"id":27,"image_id":20,"category_id":1,"segmentation":[],"area":155206.35990000004,"bbox":[412.9,5.75,196.83,788.53],"iscrowd":0,"attributes":{"occluded":false,"rotation":0.0}},{"id":28,"image_id":21,"category_id":1,"segmentation":[],"area":74666.28620000005,"bbox":[357.59,27.62,60.46,1234.97],"iscrowd":0,"attributes":{"occluded":false,"rotation":0.0}},{"id":29,"image_id":22,"category_id":1,"segmentation":[],"area":32149.243000000013,"bbox":[433.49,201.28,37.3,861.91],"iscrowd":0,"attributes":{"occluded":false,"rotation":0.0}},{"id":30,"image_id":23,"category_id":1,"segmentation":[],"area":78307.54799999998,"bbox":[419.3,35.33,75.9,1031.72],"iscrowd":0,"attributes":{"occluded":false,"rotation":0.0}},{"id":31,"image_id":24,"category_id":1,"segmentation":[],"area":19792.89260000001,"bbox":[370.45,854.79,147.94,133.79],"iscrowd":0,"attributes":{"occluded":false,"rotation":0.0}},{"id":32,"image_id":25,"category_id":1,"segmentation":[],"area":80916.39390000004,"bbox":[391.03,23.76,82.33,982.83],"iscrowd":0,"attributes":{"occluded":false,"rotation":0.0}},{"id":33,"image_id":26,"category_id":1,"segmentation":[],"area":51434.39880000002,"bbox":[328.0,458.57,237.99,216.12],"iscrowd":0,"attributes":{"occluded":false,"rotation":0.0}},{"id":34,"image_id":28,"category_id":1,"segmentation":[],"area":27457.943099999982,"bbox":[269.72,220.58,45.03,609.77],"iscrowd":0,"attributes":{"occluded":false,"rotation":0.0}},{"id":35,"image_id":29,"category_id":1,"segmentation":[],"area":3595.813200000001,"bbox":[353.34,525.47,68.18,52.74],"iscrowd":0,"attributes":{"occluded":false,"rotation":0.0}},{"id":36,"image_id":30,"category_id":1,"segmentation":[],"area":263454.8606,"bbox":[423.97,134.39,515.86,510.71],"iscrowd":0,"attributes":{"occluded":false,"rotation":0.0}},{"id":37,"image_id":31,"category_id":1,"segmentation":[],"area":471697.94360000006,"bbox":[351.93,81.65,580.18,813.02],"iscrowd":0,"attributes":{"occluded":false,"rotation":0.0}},{"id":38,"image_id":32,"category_id":1,"segmentation":[],"area":119686.0284,"bbox":[305.61,292.62,290.74,411.66],"iscrowd":0,"attributes":{"occluded":false,"rotation":0.0}},{"id":39,"image_id":33,"category_id":1,"segmentation":[],"area":747518.382,"bbox":[291.46,58.49,616.2,1213.11],"iscrowd":0,"attributes":{"occluded":false,"rotation":0.0}},{"id":40,"image_id":34,"category_id":1,"segmentation":[],"area":61615.64660000001,"bbox":[354.5,318.35,133.79,460.54],"iscrowd":0,"attributes":{"occluded":false,"rotation":0.0}},{"id":41,"image_id":35,"category_id":1,"segmentation":[],"area":196959.09300000002,"bbox":[375.08,346.65,298.45,659.94],"iscrowd":0,"attributes":{"occluded":false,"rotation":0.0}},{"id":42,"image_id":36,"category_id":1,"segmentation":[],"area":21001.334199999972,"bbox":[492.66,381.38,57.89,362.78],"iscrowd":0,"attributes":{"occluded":false,"rotation":0.0}},{"id":43,"image_id":37,"category_id":1,"segmentation":[],"area":46110.54079999998,"bbox":[328.0,917.83,240.56,191.68],"iscrowd":0,"attributes":{"occluded":false,"rotation":0.0}},{"id":44,"image_id":38,"category_id":1,"segmentation":[],"area":24943.29499999999,"bbox":[373.02,529.32,123.5,201.97],"iscrowd":0,"attributes":{"occluded":false,"rotation":0.0}},{"id":45,"image_id":39,"category_id":1,"segmentation":[],"area":96894.01539999997,"bbox":[484.27,406.62,267.53,362.18],"iscrowd":0,"attributes":{"occluded":false,"rotation":0.0}},{"id":46,"image_id":40,"category_id":1,"segmentation":[],"area":38194.546700000006,"bbox":[240.13,301.63,189.11,201.97],"iscrowd":0,"attributes":{"occluded":false,"rotation":0.0}},{"id":47,"image_id":41,"category_id":1,"segmentation":[],"area":4822.289600000003,"bbox":[314.49,571.78,79.76,60.46],"iscrowd":0,"attributes":{"occluded":false,"rotation":0.0}},{"id":48,"image_id":42,"category_id":1,"segmentation":[],"area":34033.53099999998,"bbox":[407.76,639.96,57.89,587.9],"iscrowd":0,"attributes":{"occluded":false,"rotation":0.0}},{"id":49,"image_id":43,"category_id":1,"segmentation":[],"area":2366.1630000000014,"bbox":[493.95,575.64,28.3,83.61],"iscrowd":0,"attributes":{"occluded":false,"rotation":0.0}},{"id":50,"image_id":44,"category_id":1,"segmentation":[],"area":3336.1723999999986,"bbox":[535.11,510.03,36.02,92.62],"iscrowd":0,"attributes":{"occluded":false,"rotation":0.0}},{"id":51,"image_id":45,"category_id":1,"segmentation":[],"area":1981.3765999999998,"bbox":[603.29,584.64,27.02,73.33],"iscrowd":0,"attributes":{"occluded":false,"rotation":0.0}},{"id":52,"image_id":46,"category_id":1,"segmentation":[],"area":6242.898199999991,"bbox":[414.19,627.09,105.49,59.18],"iscrowd":0,"attributes":{"occluded":false,"rotation":0.0}},{"id":53,"image_id":47,"category_id":1,"segmentation":[],"area":37298.778000000006,"bbox":[387.17,481.73,151.8,245.71],"iscrowd":0,"attributes":{"occluded":false,"rotation":0.0}},{"id":54,"image_id":48,"category_id":1,"segmentation":[],"area":19149.511999999995,"bbox":[446.35,530.61,111.92,171.1],"iscrowd":0,"attributes":{"occluded":false,"rotation":0.0}},{"id":55,"image_id":49,"category_id":1,"segmentation":[],"area":28995.6516,"bbox":[383.31,645.1,154.38,187.82],"iscrowd":0,"attributes":{"occluded":false,"rotation":0.0}},{"id":56,"image_id":50,"category_id":1,"segmentation":[],"area":33066.29199999997,"bbox":[439.92,225.73,47.6,694.67],"iscrowd":0,"attributes":{"occluded":false,"rotation":0.0}},{"id":57,"image_id":51,"category_id":1,"segmentation":[],"area":16056.095099999995,"bbox":[465.65,695.27,54.03,297.17],"iscrowd":0,"attributes":{"occluded":false,"rotation":0.0}},{"id":58,"image_id":52,"category_id":1,"segmentation":[],"area":2020.620000000003,"bbox":[541.55,802.05,42.45,47.6],"iscrowd":0,"attributes":{"occluded":false,"rotation":0.0}},{"id":59,"image_id":53,"category_id":1,"segmentation":[],"area":1392.036099999996,"bbox":[482.37,654.11,37.31,37.31],"iscrowd":0,"attributes":{"occluded":false,"rotation":0.0}},{"id":60,"image_id":54,"category_id":1,"segmentation":[],"area":19904.905600000002,"bbox":[383.31,525.47,159.52,124.78],"iscrowd":0,"attributes":{"occluded":false,"rotation":0.0}},{"id":61,"image_id":56,"category_id":1,"segmentation":[],"area":40774.63999999999,"bbox":[420.62,113.81,70.75,576.32],"iscrowd":0,"attributes":{"occluded":false,"rotation":0.0}},{"id":62,"image_id":57,"category_id":1,"segmentation":[],"area":3162.7167999999992,"bbox":[430.91,409.69,63.04,50.17],"iscrowd":0,"attributes":{"occluded":false,"rotation":0.0}},{"id":63,"image_id":59,"category_id":1,"segmentation":[],"area":48330.195199999995,"bbox":[376.75,399.91,126.07,383.36],"iscrowd":0,"attributes":{"occluded":false,"rotation":0.0}},{"id":64,"image_id":60,"category_id":1,"segmentation":[],"area":33929.555400000005,"bbox":[403.9,416.12,65.61,517.14],"iscrowd":0,"attributes":{"occluded":false,"rotation":0.0}},{"id":65,"image_id":61,"category_id":1,"segmentation":[],"area":26940.467999999983,"bbox":[397.47,374.95,56.6,475.98],"iscrowd":0,"attributes":{"occluded":false,"rotation":0.0}},{"id":66,"image_id":62,"category_id":1,"segmentation":[],"area":20086.93890000001,"bbox":[469.51,425.12,131.21,153.09],"iscrowd":0,"attributes":{"occluded":false,"rotation":0.0}},{"id":67,"image_id":63,"category_id":1,"segmentation":[],"area":74359.45,"bbox":[384.6,368.52,168.52,441.25],"iscrowd":0,"attributes":{"occluded":false,"rotation":0.0}},{"id":68,"image_id":64,"category_id":1,"segmentation":[],"area":198902.69359999997,"bbox":[411.62,21.18,164.66,1207.96],"iscrowd":0,"attributes":{"occluded":false,"rotation":0.0}},{"id":69,"image_id":65,"category_id":1,"segmentation":[],"area":17476.485,"bbox":[394.89,516.46,123.5,141.51],"iscrowd":0,"attributes":{"occluded":false,"rotation":0.0}},{"id":70,"image_id":66,"category_id":1,"segmentation":[],"area":24083.311999999947,"bbox":[509.38,18.61,19.3,1247.84],"iscrowd":0,"attributes":{"occluded":false,"rotation":0.0}},{"id":71,"image_id":67,"category_id":1,"segmentation":[],"area":51163.430999999975,"bbox":[547.98,215.44,75.9,674.09],"iscrowd":0,"attributes":{"occluded":false,"rotation":0.0}},{"id":72,"image_id":68,"category_id":1,"segmentation":[],"area":1921.2636000000027,"bbox":[420.62,686.27,34.73,55.32],"iscrowd":0,"attributes":{"occluded":false,"rotation":0.0}},{"id":73,"image_id":69,"category_id":1,"segmentation":[],"area":10673.582399999996,"bbox":[384.6,453.43,110.63,96.48],"iscrowd":0,"attributes":{"occluded":false,"rotation":0.0}},{"id":74,"image_id":70,"category_id":1,"segmentation":[],"area":18096.414000000015,"bbox":[438.63,793.04,104.2,173.67],"iscrowd":0,"attributes":{"occluded":false,"rotation":0.0}},{"id":75,"image_id":70,"category_id":1,"segmentation":[],"area":3723.163199999998,"bbox":[457.93,266.89,38.59,96.48],"iscrowd":0,"attributes":{"occluded":false,"rotation":0.0}},{"id":76,"image_id":71,"category_id":1,"segmentation":[],"area":36208.84680000001,"bbox":[380.74,332.5,65.61,551.88],"iscrowd":0,"attributes":{"occluded":false,"rotation":0.0}},{"id":77,"image_id":72,"category_id":1,"segmentation":[],"area":2409.738,"bbox":[438.63,475.29,36.02,66.9],"iscrowd":0,"attributes":{"occluded":false,"rotation":0.0}},{"id":78,"image_id":73,"category_id":1,"segmentation":[],"area":112629.75999999997,"bbox":[361.45,362.09,219.98,512.0],"iscrowd":0,"attributes":{"occluded":false,"rotation":0.0}},{"id":79,"image_id":74,"category_id":1,"segmentation":[],"area":11662.063999999988,"bbox":[608.44,513.89,104.2,111.92],"iscrowd":0,"attributes":{"occluded":false,"rotation":0.0}},{"id":80,"image_id":76,"category_id":1,"segmentation":[],"area":19375.236100000024,"bbox":[286.83,275.9,29.59,654.79],"iscrowd":0,"attributes":{"occluded":false,"rotation":0.0}},{"id":81,"image_id":77,"category_id":1,"segmentation":[],"area":10430.973000000022,"bbox":[295.84,437.99,20.58,506.85],"iscrowd":0,"attributes":{"occluded":false,"rotation":0.0}},{"id":82,"image_id":78,"category_id":1,"segmentation":[],"area":2343.0330000000013,"bbox":[264.96,588.5,75.9,30.87],"iscrowd":0,"attributes":{"occluded":false,"rotation":0.0}},{"id":83,"image_id":79,"category_id":1,"segmentation":[],"area":331.41099999999835,"bbox":[321.29,565.14,9.05,36.62],"iscrowd":0,"attributes":{"occluded":false,"rotation":0.0}},{"id":84,"image_id":80,"category_id":1,"segmentation":[],"area":27396.251999999968,"bbox":[501.38,13.88,37.05,739.44],"iscrowd":0,"attributes":{"occluded":false,"rotation":0.0}},{"id":85,"image_id":80,"category_id":1,"segmentation":[],"area":19351.384800000014,"bbox":[309.96,10.79,44.77,432.24],"iscrowd":0,"attributes":{"occluded":false,"rotation":0.0}},{"id":86,"image_id":81,"category_id":1,"segmentation":[],"area":56867.93699999997,"bbox":[482.86,1.53,58.66,969.45],"iscrowd":0,"attributes":{"occluded":false,"rotation":0.0}},{"id":87,"image_id":82,"category_id":1,"segmentation":[],"area":7892.0513999999985,"bbox":[470.51,544.92,71.01,111.14],"iscrowd":0,"attributes":{"occluded":false,"rotation":0.0}},{"id":88,"image_id":83,"category_id":1,"segmentation":[],"area":369692.3412,"bbox":[195.73,175.97,467.74,790.38],"iscrowd":0,"attributes":{"occluded":false,"rotation":0.0}},{"id":89,"image_id":84,"category_id":1,"segmentation":[],"area":3802.9277999999977,"bbox":[155.59,583.51,21.61,175.98],"iscrowd":0,"attributes":{"occluded":false,"rotation":0.0}},{"id":90,"image_id":84,"category_id":1,"segmentation":[],"area":493.2339000000014,"bbox":[367.08,240.8,13.89,35.51],"iscrowd":0,"attributes":{"occluded":false,"rotation":0.0}},{"id":91,"image_id":85,"category_id":1,"segmentation":[],"area":2187.7832000000008,"bbox":[338.06,580.42,41.68,52.49],"iscrowd":0,"attributes":{"occluded":false,"rotation":0.0}},{"id":92,"image_id":86,"category_id":1,"segmentation":[],"area":1544.244000000003,"bbox":[341.15,637.54,41.68,37.05],"iscrowd":0,"attributes":{"occluded":false,"rotation":0.0}},{"id":93,"image_id":87,"category_id":1,"segmentation":[],"area":40536.00749999998,"bbox":[441.18,77.17,54.03,750.25],"iscrowd":0,"attributes":{"occluded":false,"rotation":0.0}},{"id":94,"image_id":88,"category_id":1,"segmentation":[],"area":39705.01070000001,"bbox":[404.13,37.03,52.49,756.43],"iscrowd":0,"attributes":{"occluded":false,"rotation":0.0}},{"id":95,"image_id":89,"category_id":1,"segmentation":[],"area":31656.376800000005,"bbox":[445.81,104.96,41.68,759.51],"iscrowd":0,"attributes":{"occluded":false,"rotation":0.0}},{"id":96,"image_id":90,"category_id":1,"segmentation":[],"area":222694.5305,"bbox":[165.16,237.72,368.95,603.59],"iscrowd":0,"attributes":{"occluded":false,"rotation":0.0}},{"id":97,"image_id":91,"category_id":1,"segmentation":[],"area":55310.513199999994,"bbox":[428.83,456.93,169.81,325.72],"iscrowd":0,"attributes":{"occluded":false,"rotation":0.0}},{"id":98,"image_id":92,"category_id":1,"segmentation":[],"area":338362.3559999999,"bbox":[129.71,219.19,453.8,745.62],"iscrowd":0,"attributes":{"occluded":false,"rotation":0.0}},{"id":99,"image_id":93,"category_id":1,"segmentation":[],"area":2725.9692000000023,"bbox":[390.7,512.5,33.96,80.27],"iscrowd":0,"attributes":{"occluded":false,"rotation":0.0}},{"id":100,"image_id":94,"category_id":1,"segmentation":[],"area":1382.497600000001,"bbox":[341.3,427.59,30.88,44.77],"iscrowd":0,"attributes":{"occluded":false,"rotation":0.0}},{"id":101,"image_id":95,"category_id":1,"segmentation":[],"area":368994.92490000004,"bbox":[0.0,385.91,608.21,606.69],"iscrowd":0,"attributes":{"occluded":false,"rotation":0.0}},{"id":102,"image_id":96,"category_id":1,"segmentation":[],"area":14153.5863,"bbox":[382.83,297.92,30.87,458.49],"iscrowd":0,"attributes":{"occluded":false,"rotation":0.0}},{"id":103,"image_id":97,"category_id":1,"segmentation":[],"area":471.6986000000013,"bbox":[491.08,358.77,17.66,26.71],"iscrowd":0,"attributes":{"occluded":false,"rotation":0.0}},{"id":104,"image_id":97,"category_id":1,"segmentation":[],"area":345.3559999999999,"bbox":[363.12,276.05,13.36,25.85],"iscrowd":0,"attributes":{"occluded":false,"rotation":0.0}},{"id":105,"image_id":97,"category_id":1,"segmentation":[],"area":198.6647999999997,"bbox":[374.76,400.56,7.32,27.14],"iscrowd":0,"attributes":{"occluded":false,"rotation":0.0}},{"id":106,"image_id":97,"category_id":1,"segmentation":[],"area":340.5995999999995,"bbox":[411.81,437.61,7.32,46.53],"iscrowd":0,"attributes":{"occluded":false,"rotation":0.0}},{"id":107,"image_id":97,"category_id":1,"segmentation":[],"area":32706.3429,"bbox":[260.87,549.55,225.39,145.11],"iscrowd":0,"attributes":{"occluded":false,"rotation":0.0}},{"id":108,"image_id":97,"category_id":1,"segmentation":[],"area":443.9679999999994,"bbox":[344.6,457.0,11.2,39.64],"iscrowd":0,"attributes":{"occluded":false,"rotation":0.0}}]}